gitprofile/__init__.py
gitprofile/github.py
gitprofile-0.3.dist-info/METADATA
gitprofile-0.3.dist-info/WHEEL
gitprofile-0.3.dist-info/top_level.txt
gitprofile-0.3.dist-info/RECORD
