Metadata-Version: 2.1
Name: gitprofile
Version: 0.3
Summary: Extract public repository data.
Home-page: https://github.com/euanacampbell/gitprofile
Author: Euan Campbell
Author-email: dev@euan.app
License: MIT
Download-URL: https://github.com/euanacampbell/gitprofile/archive/refs/heads/master.tar.gz
Keywords: GitHub,scraping,requests
Platform: UNKNOWN
Classifier: Development Status :: 3 - Alpha
Classifier: Intended Audience :: Developers
Classifier: Topic :: Software Development :: Build Tools
Classifier: License :: OSI Approved :: MIT License
Classifier: Programming Language :: Python :: 3
Classifier: Programming Language :: Python :: 3.4
Classifier: Programming Language :: Python :: 3.5
Classifier: Programming Language :: Python :: 3.6
Requires-Dist: requests (==2.25.1)
Requires-Dist: beautifulsoup4 (==4.9.3)
